setup.py
aux_db/__init__.py
aux_db/db.py
aux_db.egg-info/PKG-INFO
aux_db.egg-info/SOURCES.txt
aux_db.egg-info/dependency_links.txt
aux_db.egg-info/requires.txt
aux_db.egg-info/top_level.txt