Metadata-Version: 1.1
Name: aux-db
Version: 0.0.4
Summary: an auxiliary sqlserver tool
Home-page: https://github.com/yituocpuls
Author: LiaoDingyi
Author-email: 731737792@qq.com
License: UNKNOWN
Keywords: tool,sql
Platform: window
Classifier: 
